Xelm.py
backupfile.py
bigtmp.py
chgnetworkinfo.py
chkrpms.py
csgetcfg.py
csinsertcopyright.py
csmain.py
csmenu.py
cssecscan.py
csstatmap.py
deliver_post.py
djbdhcpgen.py
dnsmap.py
dnsnextip.py
emailcheck.py
findcritical.py
gdfspace.py
getglobals.py
mapnics.py
mkUserRsyncConfs.py
mounted.py
nfpipe.py
pflogsumm_cleanup.py
psmailq.py
putty2sshpub.py
rmopkgenv.py
rpmgetopts.py
setup.cfg
setup.py
stripcomments.py
termcapcmp.py
tw.djbdns_files.py
twgenconfig.py
undelsend.py
uniqlines.py
whlserver.py
./Curses.py
./Dates.py
./Edits.py
./Fields.py
./FixedPoint.py
./Getopts.py
./LockFile.py
./MailInternet.py
./Netparams.py
./OPKG.py
./Parsebraces.py
./Passwd.py
./ReportPrint.py
./SysUtils.py
./Syslog.py
./Termcap.py
./Xelm.py
./__init__.py
./abbr2state.py
./backupfile.py
./bigtmp.py
./chgnetworkinfo.py
./chkrpms.py
./csadmin.py
./csgetcfg.py
./csinsertcopyright.py
./csmain.py
./csmenu.py
./cssecscan.py
./csstatmap.py
./deliver_post.py
./djbdhcpgen.py
./dnsmap.py
./dnsnextip.py
./emailcheck.py
./findcritical.py
./gdfspace.py
./getglobals.py
./mapnics.py
./mkUserRsyncConfs.py
./mounted.py
./nfpipe.py
./pflogsumm_cleanup.py
./psmailq.py
./putty2sshpub.py
./rmopkgenv.py
./rpmgetopts.py
./spamd.py
./stripcomments.py
./termcapcmp.py
./tw.djbdns_files.py
./twgenconfig.py
./undelsend.py
./uniqlines.py
./whlserver.py
./DNS/__init__.py
./DateTime/DateTime.py
./DateTime/DateTimeZone.py
./DateTime/__init__.py
./LDAP/Passwd.py
./LDAP/__init__.py
./Maildir/__init__.py
./Maildir/imap2maildir.py
./Maildir/mbox2maildir.py
./Spamassassin/__init__.py
Csys.egg-info/PKG-INFO
Csys.egg-info/SOURCES.txt
Csys.egg-info/dependency_links.txt
Csys.egg-info/entry_points.txt
Csys.egg-info/not-zip-safe
Csys.egg-info/top_level.txt
Maildir/imap2maildir.py
Maildir/mbox2maildir.py