Metadata-Version: 1.0
Name: Csys
Version: 1.25
Summary: Celestial's Python Utilities
Home-page: http://www.celestial.com
Author: Bill Campbell
Author-email: support@celestial.com
License: GPL
Platform: UNKNOWN
